miqsel/__init__.py
miqsel/config.py
miqsel/server.py
miqsel-3.3.dist-info/LICENSE
miqsel-3.3.dist-info/METADATA
miqsel-3.3.dist-info/WHEEL
miqsel-3.3.dist-info/entry_points.txt
miqsel-3.3.dist-info/top_level.txt
miqsel-3.3.dist-info/RECORD
