Metadata-Version: 2.1
Name: miqsel
Version: 3.3
Summary: miqsel is a Python CLI utility leaveraging a Selenium container image to efficiently manage a Selenium server for streamlined testing wrokflows.
Author-email: Nikhil Dhandre <nik.digitronik@live.com>
License: miqsel
Project-URL: repository, https://github.com/digitronik/miqsel
Keywords: miqsel,selenium
Classifier: Programming Language :: Python
Classifier: Programming Language :: Python :: 3
Classifier: Programming Language :: Python :: 3.8
Classifier: Programming Language :: Python :: 3.9
Classifier: Programming Language :: Python :: 3.10
Classifier: Programming Language :: Python :: Implementation :: CPython
Classifier: Programming Language :: Python :: Implementation :: PyPy
Classifier: Topic :: Software Development :: Libraries :: Python Modules
Classifier: Topic :: Software Development :: Quality Assurance
Classifier: Topic :: Software Development :: Testing
Requires-Python: >=3.8
License-File: LICENSE
Requires-Dist: Click >=5.0
Provides-Extra: dev
Requires-Dist: pre-commit ; extra == 'dev'
Requires-Dist: pytest ; extra == 'dev'
Requires-Dist: pytest-cov ; extra == 'dev'
